MANIFEST.in
README.md
requirements.txt
setup.cfg
setup.py
napalm_ruckus_fastiron/FastIron.py
napalm_ruckus_fastiron/__init__.py
napalm_ruckus_fastiron.egg-info/PKG-INFO
napalm_ruckus_fastiron.egg-info/SOURCES.txt
napalm_ruckus_fastiron.egg-info/dependency_links.txt
napalm_ruckus_fastiron.egg-info/requires.txt
napalm_ruckus_fastiron.egg-info/top_level.txt
napalm_ruckus_fastiron/utils/__init__.py