Metadata-Version: 1.1
Name: napalm-ruckus-fastiron
Version: 1.0.26
Summary: Network Automation and Programmability Abstraction Layer with Multivendor support
Home-page: https://github.com/Static0verride/napalm-ruckus-fastiron
Author: Jesus Mendez
Author-email: mendezj@staticoverride.us
License: UNKNOWN
Platform: UNKNOWN
Classifier: Topic :: Utilities
Classifier: Programming Language :: Python
Classifier: Programming Language :: Python :: 2
Classifier: Programming Language :: Python :: 2.7
Classifier: Operating System :: POSIX :: Linux
Classifier: Operating System :: MacOS
